{
  "length": 1.0,
  "parts": {
    "leftWing": {
      "rotation": [
        {
          "time": 0.0,
          "transform": [
            0.0,
            0.0,
            0.0
          ]
        },
        {
          "interpolation": {
            "type": "minecraft:catmullrom"
          },
          "time": 0.25,
          "transform": [
            14.896902,
            14.896902,
            0.0
          ]
        },
        {
          "interpolation": {
            "type": "minecraft:catmullrom"
          },
          "time": 0.5,
          "transform": [
            7.448451,
            7.448451,
            0.0
          ]
        },
        {
          "interpolation": {
            "type": "minecraft:catmullrom"
          },
          "time": 0.75,
          "transform": [
            14.896902,
            14.896902,
            0.0
          ]
        },
        {
          "interpolation": {
            "type": "minecraft:catmullrom"
          },
          "time": 1.0,
          "transform": [
            0.0,
            0.0,
            0.0
          ]
        }
      ]
    },
    "rightWing": {
      "rotation": [
        {
          "time": 0.0,
          "transform": [
            0.0,
            0.0,
            0.0
          ]
        },
        {
          "interpolation": {
            "type": "minecraft:catmullrom"
          },
          "time": 0.25,
          "transform": [
            14.896902,
            -14.896902,
            0.0
          ]
        },
        {
          "interpolation": {
            "type": "minecraft:catmullrom"
          },
          "time": 0.5,
          "transform": [
            7.448451,
            -7.448451,
            0.0
          ]
        },
        {
          "interpolation": {
            "type": "minecraft:catmullrom"
          },
          "time": 0.75,
          "transform": [
            14.896902,
            -14.896902,
            0.0
          ]
        },
        {
          "interpolation": {
            "type": "minecraft:catmullrom"
          },
          "time": 1.0,
          "transform": [
            0.0,
            0.0,
            0.0
          ]
        }
      ]
    }
  }
}